autobi/__init__.py
autobi/arguments_builder.py
autobi/dataset_builder.py
autobi/featurenames_builder.py
autobi/run_default.py
autobi/train_default.py
autobi/_jar/AuToBIAdapter-0.1.2.jar
autobi/_jar/__init__.py
autobi/_jar/__init__.pyi
autobi/core/__init__.py
autobi/core/jvm_adapters.py
autobi/core/jvm_view.py
autobi/core/jvm_view.pyi
autobi/core/not_instantiable.py
autobi/core/printing_service.py
autobi_py-0.2.2.dist-info/METADATA
autobi_py-0.2.2.dist-info/WHEEL
autobi_py-0.2.2.dist-info/top_level.txt
autobi_py-0.2.2.dist-info/RECORD
