Metadata-Version: 2.1
Name: autobi_py
Version: 0.2.2
Summary: A python wrapper and interface around AuToBI
Author-email: JJWRoeloffs <jelleroeloffs@gmail.com>
Project-URL: Homepage, https://github.com/JJWRoeloffs/autobi_py
Project-URL: Bug Tracker, https://github.com/JJWRoeloffs/autobi_py/issues
Classifier: Programming Language :: Python :: 3
Classifier: License :: OSI Approved :: MIT License
Classifier: Operating System :: OS Independent
Requires-Python: >=3.9
Requires-Dist: py4j ~=0.10.9.7
Requires-Dist: pandas ~=2.1
